{
    "status": "success",
    "message": "ok",
    "rowCount": 6,
    "data": [
        {
            "EczaneAdi": "Tuğba Eczanesi",
            "Adresi": "Hükümet Caddesi No:71/B Eflani / Karabük",
            "Semt": "",
            "YolTarifi": "",
            "Telefon": "0(370)461-24-27",
            "Telefon2": "",
            "Sehir": "Karabük",
            "ilce": "Eflani",
            "latitude": 41.4232,
            "longitude": 32.9589
        },
        {
            "EczaneAdi": "Eskipazar Eczanesi",
            "Adresi": "Merkez Mahallesi, Cami Caddesi, No:16 Eskipazar / Karabük",
            "Semt": "",
            "YolTarifi": "",
            "Telefon": "0(370)818-37-37",
            "Telefon2": "",
            "Sehir": "Karabük",
            "ilce": "Eskipazar",
            "latitude": 40.944,
            "longitude": 32.5311
        },
        {
            "EczaneAdi": "Gökçınar Eczanesi",
            "Adresi": "100.Yıl Mahallesi 3 Nolu Cadde Bahçeşehir Sitesi A Blok No:4 Karabük",
            "Semt": "5000 Evler",
            "YolTarifi": "",
            "Telefon": "0(370)433-71-19",
            "Telefon2": "",
            "Sehir": "Karabük",
            "ilce": "Merkez",
            "latitude": 41.2183,
            "longitude": 32.668
        },
        {
            "EczaneAdi": "İrem Eczanesi",
            "Adresi": "Sırınevler Mahallesi Alparslan Caddesi Sevim Apt No:2/B Merkez / Karabük",
            "Semt": "",
            "YolTarifi": "",
            "Telefon": "0(370)415-55-60",
            "Telefon2": "",
            "Sehir": "Karabük",
            "ilce": "Merkez",
            "latitude": 41.208635,
            "longitude": 32.620142
        },
        {
            "EczaneAdi": "Canan Aslan Eczanesi",
            "Adresi": "Atatürk Mahallesi, Sağlık Sokak, No:38/1-C Safranbolu / Karabük",
            "Semt": "",
            "YolTarifi": "",
            "Telefon": "0(370)712-12-26",
            "Telefon2": "",
            "Sehir": "Karabük",
            "ilce": "Safranbolu",
            "latitude": 41.252121,
            "longitude": 32.684575
        },
        {
            "EczaneAdi": "Gökçe Eczanesi",
            "Adresi": "İnönü Caddesi No:2 Yenice / Karabük",
            "Semt": "",
            "YolTarifi": "",
            "Telefon": "0(370)766-44-55",
            "Telefon2": "",
            "Sehir": "Karabük",
            "ilce": "Yenice",
            "latitude": 41.199755,
            "longitude": 32.329945
        }
    ]
}